spark_insights/__init__.py
spark_insights/report_generator.py
spark_insights/utils.py
spark_insights-1.1.dist-info/METADATA
spark_insights-1.1.dist-info/WHEEL
spark_insights-1.1.dist-info/top_level.txt
spark_insights-1.1.dist-info/RECORD
